QuickEcharts/Charts.py
QuickEcharts/__init__.py
QuickEcharts/test_functions.py
QuickEcharts/shiny_app/__init__.py
QuickEcharts/shiny_app/app.py
QuickEcharts/shiny_app/modules/__init__.py
QuickEcharts/shiny_app/modules/schemas.py
QuickEcharts/shiny_app/www/styles.css
quickecharts-2.1.8.dist-info/licenses/LICENSE
quickecharts-2.1.8.dist-info/METADATA
quickecharts-2.1.8.dist-info/WHEEL
quickecharts-2.1.8.dist-info/top_level.txt
quickecharts-2.1.8.dist-info/RECORD
