Metadata-Version: 2.4
Name: QuickEcharts
Version: 2.1.8
Summary: Create ECharts plots in a single simple function call, with internal data wrangling via polars
Home-page: https://github.com/AdrianAntico/QuickEcharts
Author: Adrian Antico
Author-email: adrianantico@gmail.com
License: MIT
Classifier: Development Status :: 4 - Beta
Classifier: License :: OSI Approved :: MIT License
Classifier: Programming Language :: Python
Classifier: Programming Language :: Python :: 3
Classifier: Programming Language :: Python :: 3.10
Classifier: Programming Language :: Python :: 3.11
Classifier: Programming Language :: Python :: 3.12
Classifier: Programming Language :: Python :: 3.13
Classifier: Programming Language :: Python :: 3.14
Classifier: Operating System :: OS Independent
Classifier: Intended Audience :: Developers
Classifier: Intended Audience :: Science/Research
Classifier: Topic :: Scientific/Engineering :: Visualization
Requires-Python: >=3.10
License-File: LICENSE
Requires-Dist: pyecharts
Requires-Dist: polars>=1.0.0
Requires-Dist: numpy
Requires-Dist: shiny
Dynamic: author
Dynamic: author-email
Dynamic: classifier
Dynamic: description
Dynamic: description-content-type
Dynamic: home-page
Dynamic: license
Dynamic: license-file
Dynamic: requires-dist
Dynamic: requires-python
Dynamic: summary
